[
  {
    "name": "neck",
    "name_ar": "الرقبة"
  },
  {
    "name": "lower arms",
    "name_ar": "الذراعان"
  },
  {
    "name": "shoulders",
    "name_ar": "الأكتاف"
  },
  {
    "name": "cardio",
    "name_ar": "كارديو"
  },
  {
    "name": "upper arms",
    "name_ar": "الذراعان"
  },
  {
    "name": "chest",
    "name_ar": "الصدر"
  },
  {
    "name": "lower legs",
    "name_ar": "الساقان"
  },
  {
    "name": "back",
    "name_ar": "الظهر"
  },
  {
    "name": "upper legs",
    "name_ar": "الأرجل"
  },
  {
    "name": "waist",
    "name_ar": "الخصر"
  }
]
